[
    {
        "event": "Concert",
        "client_name": "John",
        "price": 50,
        "ticket_id": 1
    },
    {
        "event": "Concert",
        "client_name": "Mark",
        "price": 25.0,
        "ticket_id": 2
    },
    {
        "event": "Concert",
        "client_name": "John",
        "price": 50,
        "ticket_id": 3
    },
    {
        "event": "Concert",
        "client_name": "Mark",
        "price": 25.0,
        "ticket_id": 4
    },
    {
        "event": "Concert",
        "client_name": "John",
        "price": 50,
        "ticket_id": 5
    },
    {
        "event": "Concert",
        "client_name": "Mark",
        "price": 25.0,
        "ticket_id": 6
    },
    {
        "event": "Concert",
        "client_name": "John",
        "price": 50,
        "ticket_id": 7
    },
    {
        "event": "Concert",
        "client_name": "Mark",
        "price": 25.0,
        "ticket_id": 8
    }
]